tidy3d_mcp/__init__.py
tidy3d_mcp/server.py
tidy3d_mcp/tools/__init__.py
tidy3d_mcp/tools/_dispatcher.py
tidy3d_mcp/tools/_viewers.py
tidy3d_mcp/tools/screenshots.py
tidy3d_mcp/tools/viewer.py
tidy3d_mcp/utils.py
tidy3d_mcp-0.15.4.dist-info/WHEEL
tidy3d_mcp-0.15.4.dist-info/entry_points.txt
tidy3d_mcp-0.15.4.dist-info/METADATA
tidy3d_mcp-0.15.4.dist-info/RECORD
