Metadata-Version: 2.3
Name: tidy3d-mcp
Version: 0.15.4
Summary: Local stdio FastMCP server for Tidy3D
Author: Flexcompute
License: Proprietary
Requires-Dist: fastmcp>=2.12.3
Requires-Python: >=3.10
